README.md
setup.py
ustack_etl/__init__.py
ustack_etl/etl.py
ustack_etl/mongo.py
ustack_etl/sql.py
ustack_etl/testing.py
ustack_etl.egg-info/PKG-INFO
ustack_etl.egg-info/SOURCES.txt
ustack_etl.egg-info/dependency_links.txt
ustack_etl.egg-info/top_level.txt