Metadata-Version: 1.0
Name: ustack-etl
Version: 0.1.0
Summary: Framework for writing ETL processes from MongoDB to SQL
Home-page: https://github.com/ustudio/ustack-etl
Author: UNKNOWN
Author-email: UNKNOWN
License: UNKNOWN
Platform: UNKNOWN
